deathbycaptcha/__init__.py
deathbycaptcha/deathbycaptcha.py
deathbycaptcha-0.1.0.dist-info/METADATA
deathbycaptcha-0.1.0.dist-info/WHEEL
deathbycaptcha-0.1.0.dist-info/top_level.txt
deathbycaptcha-0.1.0.dist-info/RECORD
