Metadata-Version: 2.1
Name: deathbycaptcha
Version: 0.1.0
Summary: python API for deathbycaptcha.com
Home-page: https://github.com/hyan15/python-deathbycaptcha
Author: Sergey Kolchin
Author-email: qwang16@olivetuniversity.edu
License: BSD License (New BSD License)
Platform: UNKNOWN
